napari_plugin_engine/__init__.py
napari_plugin_engine/_testsupport.py
napari_plugin_engine/_tracing.py
napari_plugin_engine/_version.py
napari_plugin_engine/callers.py
napari_plugin_engine/dist.py
napari_plugin_engine/exceptions.py
napari_plugin_engine/hooks.py
napari_plugin_engine/implementation.py
napari_plugin_engine/manager.py
napari_plugin_engine/markers.py
napari_plugin_engine-0.2.0.dist-info/LICENSE
napari_plugin_engine-0.2.0.dist-info/METADATA
napari_plugin_engine-0.2.0.dist-info/WHEEL
napari_plugin_engine-0.2.0.dist-info/entry_points.txt
napari_plugin_engine-0.2.0.dist-info/top_level.txt
napari_plugin_engine-0.2.0.dist-info/RECORD
